dimschema/VERSION.py
dimschema/__init__.py
dimschema/main_cli.py
dimschema/core/__init__.py
dimschema/core/fmanager.py
dimschema/core/queries.py
dimschema/core/utils.py
dimschema/tests/__init__.py
dimschema/tests/quicktest.py
dimschema/tests/test_one.py
gbqschema/VERSION.py
gbqschema/__init__.py
gbqschema/main_cli.py
gbqschema/settings.py
gbqschema/core/__init__.py
gbqschema/core/queries.py
gbqschema/core/storage.py
gbqschema/tests/__init__.py
gbqschema/tests/quicktest.py
gbqschema/tests/test_one.py
dimschema-0.3.dist-info/LICENSE
dimschema-0.3.dist-info/METADATA
dimschema-0.3.dist-info/WHEEL
dimschema-0.3.dist-info/entry_points.txt
dimschema-0.3.dist-info/top_level.txt
dimschema-0.3.dist-info/RECORD
