Metadata-Version: 2.1
Name: dimschema
Version: 0.3
Summary: dimschema
Home-page: https://github.com/lambdamusic/dimschema
License: UNKNOWN
Platform: UNKNOWN
License-File: LICENSE
Requires-Dist: click
Requires-Dist: pandas
Requires-Dist: tabulate
Requires-Dist: pandas-gbq
Requires-Dist: google-cloud-bigquery
